{
  "finalCTA": {
    "title": "Contacta con Soporte",
    "description": "Todas tus preguntas respondidas. Comunícate con nuestro equipo.",
    "actions": [
      {
        "type": "primary",
        "text": "Enviar mensaje"
      },
      {
        "type": "secondary",
        "text": "Descargar tradicional"
      }
    ],
    "contact": {
      "email": "info@jocarsa.com",
      "fields": [
        {
          "name": "nombre",
          "type": "text",
          "required": "true"
        },
        {
          "name": "email",
          "type": "email",
          "required": "true"
        },
        {
          "name": "mensaje",
          "type": "textarea",
          "required": "true"
        }
      ]
    }
  }
}